ocp_tessellate/__init__.py
ocp_tessellate/_version.py
ocp_tessellate/cad_objects.py
ocp_tessellate/convert.py
ocp_tessellate/defaults.py
ocp_tessellate/ocp_utils.py
ocp_tessellate/stepreader.py
ocp_tessellate/tessellator.py
ocp_tessellate/trace.py
ocp_tessellate/utils.py
ocp_tessellate_orion-0.0.1.dist-info/METADATA
ocp_tessellate_orion-0.0.1.dist-info/WHEEL
ocp_tessellate_orion-0.0.1.dist-info/top_level.txt
ocp_tessellate_orion-0.0.1.dist-info/RECORD
